noobdev/__init__.py
noobdev/_modidx.py
noobdev/card.py
noobdev/core.py
noobdev/deck.py
noobdev-0.0.1.dist-info/LICENSE
noobdev-0.0.1.dist-info/METADATA
noobdev-0.0.1.dist-info/WHEEL
noobdev-0.0.1.dist-info/entry_points.txt
noobdev-0.0.1.dist-info/top_level.txt
noobdev-0.0.1.dist-info/RECORD
