Metadata-Version: 2.1
Name: noobdev
Version: 0.0.1
Summary: testdrive
Home-page: https://github.com/Cutecatty/noobdev/
Author: Cutecatty
Author-email: theoneandonlystreetdoodler@gmail.com
License: Apache Software License 2.0
Keywords: nbdev
Classifier: Development Status :: 3 - Alpha
Classifier: Intended Audience :: Developers
Classifier: Natural Language :: English
Classifier: Programming Language :: Python :: 3.7
Classifier: Programming Language :: Python :: 3.8
Classifier: Programming Language :: Python :: 3.9
Classifier: Programming Language :: Python :: 3.10
Classifier: License :: OSI Approved :: Apache Software License
Requires-Python: >=3.7
License-File: LICENSE
Provides-Extra: dev
